django_db_anonymiser/database_sanitizer/__init__.py
django_db_anonymiser/database_sanitizer/__main__.py
django_db_anonymiser/database_sanitizer/config.py
django_db_anonymiser/database_sanitizer/dump/__init__.py
django_db_anonymiser/database_sanitizer/dump/mysql.py
django_db_anonymiser/database_sanitizer/dump/postgres.py
django_db_anonymiser/database_sanitizer/sanitizers/__init__.py
django_db_anonymiser/database_sanitizer/sanitizers/constant.py
django_db_anonymiser/database_sanitizer/sanitizers/derived.py
django_db_anonymiser/database_sanitizer/sanitizers/string.py
django_db_anonymiser/database_sanitizer/sanitizers/times.py
django_db_anonymiser/database_sanitizer/sanitizers/user.py
django_db_anonymiser/database_sanitizer/session.py
django_db_anonymiser/database_sanitizer/tests/__init__.py
django_db_anonymiser/database_sanitizer/tests/test_config.py
django_db_anonymiser/database_sanitizer/tests/test_dump.py
django_db_anonymiser/database_sanitizer/tests/test_dump_mysql.py
django_db_anonymiser/database_sanitizer/tests/test_dump_postgres.py
django_db_anonymiser/database_sanitizer/tests/test_main.py
django_db_anonymiser/database_sanitizer/tests/test_sanitizers_constant.py
django_db_anonymiser/database_sanitizer/tests/test_sanitizers_derived.py
django_db_anonymiser/database_sanitizer/tests/test_sanitizers_string.py
django_db_anonymiser/database_sanitizer/tests/test_sanitizers_times.py
django_db_anonymiser/database_sanitizer/tests/test_sanitizers_user.py
django_db_anonymiser/database_sanitizer/tests/test_session.py
django_db_anonymiser/database_sanitizer/tests/test_utils_mysql.py
django_db_anonymiser/database_sanitizer/tests/test_utils_postgres.py
django_db_anonymiser/database_sanitizer/utils/__init__.py
django_db_anonymiser/database_sanitizer/utils/mysql.py
django_db_anonymiser/database_sanitizer/utils/postgres.py
django_db_anonymiser/db_anonymiser/__init__.py
django_db_anonymiser/db_anonymiser/faker.py
django_db_anonymiser/db_anonymiser/management/__init__.py
django_db_anonymiser-0.2.5.dist-info/METADATA
django_db_anonymiser-0.2.5.dist-info/WHEEL
django_db_anonymiser-0.2.5.dist-info/RECORD
