Metadata-Version: 2.3
Name: django-db-anonymiser
Version: 0.2.5
Summary: Django app to create configurable anonymised DB dumps.
Author: Brendan Smith
Author-email: brendan.smith@digital.trade.gov.uk
Requires-Python: >3.10.0,<4.0
Classifier: Programming Language :: Python :: 3
Classifier: Programming Language :: Python :: 3.11
Classifier: Programming Language :: Python :: 3.12
Classifier: Programming Language :: Python :: 3.13
Requires-Dist: boto3 (>=1.40.33,<2.0.0)
Requires-Dist: django (>=4.2.10,<5.0.0)
Requires-Dist: django-environ (>=0.12.0,<0.13.0)
Requires-Dist: faker (>=4.18.0)
Requires-Dist: psycopg2-binary (>=2.9.10,<3.0.0)
Requires-Dist: pymysql (>=1.1.2,<2.0.0)
Requires-Dist: pyyaml (==6.0.2)
